examples/__init__.py
pyappconf/__init__.py
pyappconf/model.py
pyappconf/encoding/__init__.py
pyappconf/encoding/ext_json.py
pyappconf/encoding/ext_toml.py
pyappconf/encoding/ext_yaml.py
pyappconf/encoding/general.py
pyappconf/py_config/__init__.py
pyappconf/py_config/generate.py
tests/__init__.py
tests/config.py
tests/generate.py
tests/os_specific.py
tests/test_copy.py
tests/test_env.py
tests/test_location.py
tests/test_placeholder.py
tests/test_py_config_generate.py
tests/test_save_load.py
tests/test_serialize.py
tests/fixtures/__init__.py
tests/fixtures/data.py
tests/fixtures/model.py
tests/fixtures/pydantic_model.py
py_app_conf-1.3.0.dist-info/LICENSE.md
py_app_conf-1.3.0.dist-info/METADATA
py_app_conf-1.3.0.dist-info/WHEEL
py_app_conf-1.3.0.dist-info/top_level.txt
py_app_conf-1.3.0.dist-info/RECORD
