Metadata-Version: 2.1
Name: py-app-conf
Version: 1.3.0
Summary: Strongly typed and validated configuration supporting multiple file types, dynamic instantiation, and environment variables
Home-page: https://github.com/nickderobertis/py-app-conf
Author: Nick DeRobertis
Author-email: whoopnip@gmail.com
License: MIT
Project-URL: Code, https://github.com/nickderobertis/py-app-conf
Project-URL: Documentation, https://nickderobertis.github.io/py-app-conf
Classifier: Development Status :: 3 - Alpha
Classifier: Intended Audience :: Developers
Classifier: Programming Language :: Python :: 3.6
Classifier: Programming Language :: Python :: 3.7
License-File: LICENSE.md
Requires-Dist: pydantic (>=1.8)
Requires-Dist: appdirs
Requires-Dist: PyYAML
Requires-Dist: toml
Requires-Dist: python-dotenv
Requires-Dist: typing-extensions
Requires-Dist: black
Requires-Dist: isort
